email_keyword_matcher/__init__.py
email_keyword_matcher-1.0.0.dist-info/LICENSE.txt
email_keyword_matcher-1.0.0.dist-info/METADATA
email_keyword_matcher-1.0.0.dist-info/WHEEL
email_keyword_matcher-1.0.0.dist-info/top_level.txt
email_keyword_matcher-1.0.0.dist-info/RECORD
