Metadata-Version: 2.1
Name: email-keyword-matcher
Version: 1.0.0
Summary: Use respond to an email to trigger specific callbacks.
Home-page: https://github.com/audrow/email-keyword-matcher
Author: Audrow Nash
Author-email: audrow@hey.com
License: MIT
Keywords: email
Platform: UNKNOWN
Classifier: Intended Audience :: Developers
Classifier: License :: OSI Approved :: MIT License
Classifier: Programming Language :: Python
Classifier: Programming Language :: Python :: 3
Classifier: Programming Language :: Python :: 3.6
Classifier: Programming Language :: Python :: 3.7
Classifier: Programming Language :: Python :: 3.8
Classifier: Natural Language :: English
Requires-Python: >=3.6
Requires-Dist: pytest
Requires-Dist: pytest-cov
Requires-Dist: pytest-flake8
Requires-Dist: pytest-mock
Requires-Dist: pep257
